codebuddie/__init__.py
codebuddie/cli.py
codebuddie/code_updater.py
codebuddie/downloader.py
codebuddie/exception_handler.py
codebuddie/logging_module.py
codebuddie/utils.py
codebuddie-0.0.3.dist-info/LICENSE
codebuddie-0.0.3.dist-info/METADATA
codebuddie-0.0.3.dist-info/WHEEL
codebuddie-0.0.3.dist-info/entry_points.txt
codebuddie-0.0.3.dist-info/top_level.txt
codebuddie-0.0.3.dist-info/RECORD
