Metadata-Version: 2.1
Name: codebuddie
Version: 0.0.3
Summary: codebuddie is a Python-based command-line interface (CLI) utility that uses OpenAI chatGPT API to help you in updating comments, docstring, module docstings in your code
Author-email: c17hawke <sunny.c17hawke@gmail.com>
License: MIT
Project-URL: Bug Tracker, https://github.com/c17hawke/codebuddie/issues
Project-URL: Documentation, https://c17hawke.github.io/codebuddie/
Project-URL: Source, https://github.com/c17hawke/codebuddie
Classifier: Operating System :: OS Independent
Classifier: Programming Language :: Python :: 3.7
Classifier: Programming Language :: Python :: 3.8
Classifier: Programming Language :: Python :: 3.9
Requires-Python: >=3.7
License-File: LICENSE
Requires-Dist: requests (==2.28.2)
Requires-Dist: openai
Requires-Dist: python-dotenv
Requires-Dist: gitpython (==3.1.31)
Provides-Extra: testing
Requires-Dist: ruff (==0.0.261) ; extra == 'testing'
Requires-Dist: pytest (>=7.2.2) ; extra == 'testing'
Requires-Dist: tox (>=4.4.11) ; extra == 'testing'
Requires-Dist: pytest-mock (>=3.10.0) ; extra == 'testing'
Requires-Dist: pytest-cov (>=4.0.0) ; extra == 'testing'
Requires-Dist: mypy (>=1.1.1) ; extra == 'testing'
